[
  {
    "source": "app.css",
    "target": "app.css",
    "type": "web",
    "checksum": "0xf958"
  },
  {
    "source": "app.js",
    "target": "app.js",
    "type": "web",
    "checksum": "0x3e99"
  },
  {
    "source": "assets/cable-data.svg",
    "target": "assets/cable-data.svg",
    "type": "web",
    "checksum": "0xe672"
  },
  {
    "source": "assets/check-bold.svg",
    "target": "assets/check-bold.svg",
    "type": "web",
    "checksum": "0x3ae9"
  },
  {
    "source": "assets/circle-outline-green.svg",
    "target": "assets/circle-outline-green.svg",
    "type": "web",
    "checksum": "0x27ea"
  },
  {
    "source": "assets/circle-outline-red.svg",
    "target": "assets/circle-outline-red.svg",
    "type": "web",
    "checksum": "0x3d03"
  },
  {
    "source": "assets/cloud-outline.svg",
    "target": "assets/cloud-outline.svg",
    "type": "web",
    "checksum": "0xb46e"
  },
  {
    "source": "assets/lightning-green.svg",
    "target": "assets/lightning-green.svg",
    "type": "web",
    "checksum": "0x3d64"
  },
  {
    "source": "assets/lightning-red.svg",
    "target": "assets/lightning-red.svg",
    "type": "web",
    "checksum": "0x8d8f"
  },
  {
    "source": "assets/printer.svg",
    "target": "assets/printer.svg",
    "type": "web",
    "checksum": "0x1622"
  },
  {
    "source": "assets/sinclair-logo.woff",
    "target": "assets/sinclair-logo.woff",
    "type": "web",
    "checksum": "0xef53"
  },
  {
    "source": "assets/zx-spectrum-zx81-soft.woff",
    "target": "assets/zx-spectrum-zx81-soft.woff",
    "type": "web",
    "checksum": "0xad6e"
  },
  {
    "source": "assets/zx-spectrum-zx81.woff",
    "target": "assets/zx-spectrum-zx81.woff",
    "type": "web",
    "checksum": "0xf7e7"
  },
  {
    "source": "client.js",
    "target": "client.js",
    "type": "web",
    "checksum": "0x7005"
  },
  {
    "source": "cloud.js",
    "target": "cloud.js",
    "type": "web",
    "checksum": "0x60a8"
  },
  {
    "source": "command.js",
    "target": "command.js",
    "type": "web",
    "checksum": "0x3044"
  },
  {
    "source": "datauri.js",
    "target": "datauri.js",
    "type": "web",
    "checksum": "0x39df"
  },
  {
    "source": "event.js",
    "target": "event.js",
    "type": "web",
    "checksum": "0xbf95"
  },
  {
    "source": "favicon.ico",
    "target": "favicon.ico",
    "type": "web",
    "checksum": "0xf79d"
  },
  {
    "source": "files.json",
    "target": "files.json",
    "type": "web",
    "checksum": "0x0000"
  },
  {
    "source": "firmware/command.py",
    "target": "command.py",
    "type": "backend",
    "checksum": "0xdf70"
  },
  {
    "source": "firmware/crc16.py",
    "target": "crc16.py",
    "type": "backend",
    "checksum": "0xdbc2"
  },
  {
    "source": "firmware/event.py",
    "target": "event.py",
    "type": "backend",
    "checksum": "0xf7a5"
  },
  {
    "source": "firmware/fileprinter.py",
    "target": "fileprinter.py",
    "type": "backend",
    "checksum": "0x0bfd"
  },
  {
    "source": "firmware/init.py",
    "target": "init.py",
    "type": "backend",
    "checksum": "0xcafb"
  },
  {
    "source": "firmware/ledprinter.py",
    "target": "ledprinter.py",
    "type": "backend",
    "checksum": "0xc299"
  },
  {
    "source": "firmware/packbits.py",
    "target": "packbits.py",
    "type": "backend",
    "checksum": "0x14c0"
  },
  {
    "source": "firmware/parallelprinter.py",
    "target": "parallelprinter.py",
    "type": "backend",
    "checksum": "0x8c34"
  },
  {
    "source": "firmware/parallelprinterdriver.py",
    "target": "parallelprinterdriver.py",
    "type": "backend",
    "checksum": "0x2f9b"
  },
  {
    "source": "firmware/phew/__init__.py",
    "target": "phew/__init__.py",
    "type": "backend",
    "checksum": "0x66aa"
  },
  {
    "source": "firmware/phew/dns.py",
    "target": "phew/dns.py",
    "type": "backend",
    "checksum": "0x1169"
  },
  {
    "source": "firmware/phew/logging.py",
    "target": "phew/logging.py",
    "type": "backend",
    "checksum": "0x6b63"
  },
  {
    "source": "firmware/phew/server.py",
    "target": "phew/server.py",
    "type": "backend",
    "checksum": "0x6bc9"
  },
  {
    "source": "firmware/phew/template.py",
    "target": "phew/template.py",
    "type": "backend",
    "checksum": "0x56da"
  },
  {
    "source": "firmware/physicalprinter.py",
    "target": "physicalprinter.py",
    "type": "backend",
    "checksum": "0xd51c"
  },
  {
    "source": "firmware/pixel.py",
    "target": "pixel.py",
    "type": "backend",
    "checksum": "0xf736"
  },
  {
    "source": "firmware/pixeldriver.py",
    "target": "pixeldriver.py",
    "type": "backend",
    "checksum": "0x3448"
  },
  {
    "source": "firmware/producerconsumer.py",
    "target": "producerconsumer.py",
    "type": "backend",
    "checksum": "0x4833"
  },
  {
    "source": "firmware/reset.py",
    "target": "reset.py",
    "type": "backend",
    "checksum": "0x915e"
  },
  {
    "source": "firmware/sd.py",
    "target": "sd.py",
    "type": "backend",
    "checksum": "0xc4a7"
  },
  {
    "source": "firmware/sdcard.py",
    "target": "sdcard.py",
    "type": "backend",
    "checksum": "0x831c"
  },
  {
    "source": "firmware/sdmanager.py",
    "target": "sdmanager.py",
    "type": "backend",
    "checksum": "0x1dec"
  },
  {
    "source": "firmware/serialprinter.py",
    "target": "serialprinter.py",
    "type": "backend",
    "checksum": "0xcc22"
  },
  {
    "source": "firmware/serialserver.py",
    "target": "serialserver.py",
    "type": "backend",
    "checksum": "0x4fad"
  },
  {
    "source": "firmware/services.py",
    "target": "services.py",
    "type": "backend",
    "checksum": "0x8d5f"
  },
  {
    "source": "firmware/settings.py",
    "target": "settings.py",
    "type": "backend",
    "checksum": "0xa1f9"
  },
  {
    "source": "firmware/system.py",
    "target": "system.py",
    "type": "backend",
    "checksum": "0xfaa6"
  },
  {
    "source": "firmware/webserver.py",
    "target": "webserver.py",
    "type": "backend",
    "checksum": "0xf3be"
  },
  {
    "source": "firmware/zxprinterdriver.py",
    "target": "zxprinterdriver.py",
    "type": "backend",
    "checksum": "0x60b7"
  },
  {
    "source": "font.min.js",
    "target": "font.min.js",
    "type": "web",
    "checksum": "0x8efb"
  },
  {
    "source": "gallery.js",
    "target": "gallery.js",
    "type": "web",
    "checksum": "0x7c10"
  },
  {
    "source": "index.html",
    "target": "index.html",
    "type": "web",
    "checksum": "0xc88e"
  },
  {
    "source": "install.js",
    "target": "install.js",
    "type": "web",
    "checksum": "0xb1f0"
  },
  {
    "source": "jsbmp.js",
    "target": "jsbmp.js",
    "type": "web",
    "checksum": "0x8294"
  },
  {
    "source": "local.js",
    "target": "local.js",
    "type": "web",
    "checksum": "0x2b42"
  },
  {
    "source": "log.js",
    "target": "log.js",
    "type": "web",
    "checksum": "0x53e9"
  },
  {
    "source": "main.py",
    "target": "main.py",
    "type": "web",
    "checksum": "0xa5a6"
  },
  {
    "source": "network.js",
    "target": "network.js",
    "type": "web",
    "checksum": "0x119a"
  },
  {
    "source": "printer.js",
    "target": "printer.js",
    "type": "web",
    "checksum": "0x1b4e"
  },
  {
    "source": "repl.js",
    "target": "repl.js",
    "type": "web",
    "checksum": "0xce2d"
  },
  {
    "source": "serial.js",
    "target": "serial.js",
    "type": "web",
    "checksum": "0xa766"
  },
  {
    "source": "settings.js",
    "target": "settings.js",
    "type": "web",
    "checksum": "0x2998"
  },
  {
    "source": "utils.js",
    "target": "utils.js",
    "type": "web",
    "checksum": "0xb725"
  },
  {
    "source": "websocket.js",
    "target": "websocket.js",
    "type": "web",
    "checksum": "0x8e19"
  }
]